odoo8_addon_server_environment_files_sample-8.0.1.0.0-py2.7-nspkg.pth
odoo_addons/server_environment_files_sample/__openerp__.py
odoo_addons/server_environment_files_sample/__init__.py
odoo_addons/server_environment_files_sample/dev/base.conf
odoo_addons/server_environment_files_sample/dev/mytopic.conf
odoo_addons/server_environment_files_sample/default/base.conf
odoo_addons/server_environment_files_sample/default/mytopic.conf
odoo_addons/server_environment_files_sample/prod/base.conf
odoo_addons/server_environment_files_sample/prod/mytopic.conf
odoo_addons/server_environment_files_sample/i18n/server_environment_files.pot
odoo_addons/server_environment_files_sample/preprod/mytopic.conf
odoo_addons/server_environment_files_sample/static/description/icon.png
odoo8_addon_server_environment_files_sample-8.0.1.0.0.dist-info/top_level.txt
odoo8_addon_server_environment_files_sample-8.0.1.0.0.dist-info/WHEEL
odoo8_addon_server_environment_files_sample-8.0.1.0.0.dist-info/RECORD
odoo8_addon_server_environment_files_sample-8.0.1.0.0.dist-info/metadata.json
odoo8_addon_server_environment_files_sample-8.0.1.0.0.dist-info/DESCRIPTION.rst
odoo8_addon_server_environment_files_sample-8.0.1.0.0.dist-info/METADATA
odoo8_addon_server_environment_files_sample-8.0.1.0.0.dist-info/namespace_packages.txt
