Metadata-Version: 2.0
Name: odoo8-addon-server-environment-files-sample
Version: 8.0.1.0.0
Summary: Example server configuration environment files repository module
Home-page: http://www.camptocamp.com
Author: UNKNOWN
Author-email: UNKNOWN
License: GPL-3 or any later version
Platform: UNKNOWN
Requires-Dist: odoo (<9.0a,>=8.0a)
Classifier: Programming Language :: Python :: 2.7
Classifier: Framework :: Odoo
Classifier: License :: OSI Approved :: GNU General Public License v3 or later (GPLv3+)
